ilyxalogger/Logger.py
ilyxalogger/__init__.py
ilyxalogger-1.5.0.dist-info/METADATA
ilyxalogger-1.5.0.dist-info/WHEEL
ilyxalogger-1.5.0.dist-info/top_level.txt
ilyxalogger-1.5.0.dist-info/RECORD
