Metadata-Version: 2.4
Name: ilyxalogger
Version: 1.5.0
Summary: This is the simplest module for quick console log output.
Home-page: https://github.com/ILYXAAA/logger
Author: ILYXAAA
Author-email: ilyagolybnichev@gmail.com
Project-URL: GitHub, https://github.com/ILYXAAA/
Keywords: logging console output colorize log
Classifier: Programming Language :: Python :: 3.11
Classifier: License :: OSI Approved :: MIT License
Classifier: Operating System :: OS Independent
Requires-Python: >=3.6
Dynamic: author
Dynamic: author-email
Dynamic: classifier
Dynamic: description
Dynamic: description-content-type
Dynamic: home-page
Dynamic: keywords
Dynamic: project-url
Dynamic: requires-python
Dynamic: summary
